odoo/addons/purchase_stock_operating_unit/README.rst
odoo/addons/purchase_stock_operating_unit/__init__.py
odoo/addons/purchase_stock_operating_unit/__manifest__.py
odoo/addons/purchase_stock_operating_unit/i18n/purchase_stock_operating_unit.pot
odoo/addons/purchase_stock_operating_unit/models/__init__.py
odoo/addons/purchase_stock_operating_unit/models/purchase.py
odoo/addons/purchase_stock_operating_unit/models/purchase_order_line.py
odoo/addons/purchase_stock_operating_unit/readme/CONTRIBUTORS.rst
odoo/addons/purchase_stock_operating_unit/readme/DESCRIPTION.rst
odoo/addons/purchase_stock_operating_unit/readme/USAGE.rst
odoo/addons/purchase_stock_operating_unit/static/description/icon.png
odoo/addons/purchase_stock_operating_unit/static/description/index.html
odoo/addons/purchase_stock_operating_unit/tests/__init__.py
odoo/addons/purchase_stock_operating_unit/tests/test_purchase_stock_operating_unit.py
odoo_addon_purchase_stock_operating_unit-15.0.1.0.0.3.dist-info/METADATA
odoo_addon_purchase_stock_operating_unit-15.0.1.0.0.3.dist-info/WHEEL
odoo_addon_purchase_stock_operating_unit-15.0.1.0.0.3.dist-info/top_level.txt
odoo_addon_purchase_stock_operating_unit-15.0.1.0.0.3.dist-info/RECORD
