Metadata-Version: 2.1
Name: odoo-addon-purchase-stock-operating-unit
Version: 15.0.1.0.0.3
Summary: Copies the operating unit of purchase picking to the stock picking
Home-page: https://github.com/OCA/operating-unit
Author: Ecosoft, Odoo Community Association (OCA)
Author-email: support@odoo-community.org
License: AGPL-3
Platform: UNKNOWN
Classifier: Programming Language :: Python
Classifier: Framework :: Odoo
Classifier: Framework :: Odoo :: 15.0
Classifier: License :: OSI Approved :: GNU Affero General Public License v3
Requires-Python: >=3.8
Requires-Dist: odoo-addon-purchase-operating-unit <15.1dev,>=15.0dev
Requires-Dist: odoo-addon-stock-operating-unit <15.1dev,>=15.0dev
Requires-Dist: odoo <15.1dev,>=15.0a
